there/__init__.py
there/py.typed
there-0.0.12.dist-info/LICENSE
there-0.0.12.dist-info/WHEEL
there-0.0.12.dist-info/METADATA
there-0.0.12.dist-info/RECORD
