Metadata-Version: 2.1
Name: there
Version: 0.0.12
Summary: Print current file and line number
Author-email: Matthias Bussonnier <bussonniermatthias@gmail.com>
Classifier: License :: OSI Approved :: MIT License
Project-URL: Home, https://github.com/Carreau/there
